{
  "code": 200,
  "data": {
      "user": {
          "id": "1116327179852972032",
          "nickname": null,
          "avatar": null
      },
      "roles": [
          "SUPER_ADMIN",
          "TEST",
          "ADMIN"
      ],
      "permissions": [
          "",
          "infra:config:create",
          "promotion:seckill-activity:update",
          "system:mail-template:query",
          "mp:draft:delete",
          "bpm:task-assign-rule:create",
          "system:user:query",
          "system:error-code:query",
          "system:dept:update",
          "bpm:model:deploy",
          "infra:api-access-log:export",
          "pay:merchant:delete",
          "trade:express-company:export",
          "infra:data-source-config:update",
          "infra:file-config:export",
          "infra:test-demo:create",
          "system:mail-account:create",
          "system:notice:update",
          "promotion:seckill-time:query",
          "mp:material:query",
          "system:mail-template:create",
          "trade:express-company:update",
          "bpm:model:import",
          "infra:api-error-log:query",
          "report:go-view-data:get-by-http",
          "system:dict:update",
          "pay:app:export",
          "promotion:seckill-time:delete",
          "mp:draft:query",
          "system:sms-log:query",
          "system:tenant:export",
          "product:brand:delete",
          "infra:api-error-log:update-status",
          "mp:message:query",
          "system:mail-account:delete",
          "promotion:seckill-activity:export",
          "infra:file:delete",
          "system:sms-template:create",
          "product:category:query",
          "pay:order:query",
          "system:menu:update",
          "mp:user:sync",
          "bpm:form:query",
          "report:go-view-project:delete",
          "mp:draft:create",
          "promotion:seckill-time:create",
          "system:user:create",
          "system:role:export",
          "pay:order:export",
          "bpm:model:update",
          "infra:file-config:update",
          "trade:express-company:query",
          "product:brand:create",
          "system:notify-message:query",
          "product:spu:query",
          "mp:material:upload-temporary",
          "system:mail-template:delete",
          "infra:job:export",
          "system:sensitive-word:delete",
          "bpm:process-definition:query",
          "infra:api-error-log:export",
          "system:sensitive-word:export",
          "mp:material:upload-news-image",
          "pay:refund:update",
          "infra:job:create",
          "market:banner:create",
          "system:sms-template:send-sms",
          "bpm:user-group:query",
          "system:dept:delete",
          "system:tenant:update",
          "mp:draft:update",
          "pay:channel:parsing",
          "system:error-code:create",
          "system:tenant-package:update",
          "promotion:discount-activity:delete",
          "system:mail-template:send-mail",
          "infra:codegen:create",
          "promotion:coupon-template:create",
          "system:sms-template:delete",
          "infra:data-source-config:delete",
          "system:notify-template:create",
          "bpm:task:query",
          "mp:tag:create",
          "system:notify-template:update",
          "infra:api-access-log:query",
          "pay:refund:query",
          "system:mail-log:query",
          "infra:redis:get-monitor-info",
          "mp:auto-reply:create",
          "system:sensitive-word:query",
          "mp:tag:update",
          "bpm:form:update",
          "product:category:create",
          "system:oauth2-client:create",
          "bpm:oa-leave:query",
          "system:sensitive-word:create",
          "promotion:reward-activity:close",
          "bpm:process-instance:cancel",
          "system:dict:export",
          "bpm:form:export",
          "system:sms-channel:create",
          "system:post:create",
          "bpm:user-group:create",
          "infra:codegen:delete",
          "infra:redis:get-key-list",
          "system:user:delete",
          "infra:job:query",
          "system:sensitive-word:update",
          "bpm:model:create",
          "system:error-code:delete",
          "product:category:delete",
          "infra:data-source-config:query",
          "system:oauth2-client:update",
          "system:permission:assign-role-data-scope",
          "pay:order:create",
          "system:tenant-package:create",
          "system:operate-log:query",
          "system:sms-log:export",
          "promotion:coupon-template:update",
          "promotion:seckill-time:update",
          "market:banner:query",
          "system:sms-channel:delete",
          "system:tenant-package:query",
          "system:oauth2-client:query",
          "mp:auto-reply:delete",
          "system:operate-log:export",
          "mp:auto-reply:query",
          "mp:account:update",
          "system:role:query",
          "pay:refund:export",
          "promotion:discount-activity:query",
          "promotion:seckill-time:export",
          "mp:tag:sync",
          "system:sms-template:update",
          "system:menu:query",
          "infra:file-config:query",
          "infra:config:export",
          "pay:refund:delete",
          "bpm:oa-leave:create",
          "infra:file-config:create",
          "system:mail-template:update",
          "system:user:export",
          "bpm:user-group:delete",
          "promotion:sekill-activity:close",
          "bpm:process-instance:create",
          "trade:express-company:create",
          "report:go-view-data:get-by-sql",
          "system:dept:query",
          "mp:account:query",
          "system:tenant-package:delete",
          "product:brand:query",
          "system:role:delete",
          "system:dept:create",
          "bpm:task-assign-rule:query",
          "mp:material:upload-permanent",
          "system:menu:create",
          "system:tenant:query",
          "infra:codegen:download",
          "infra:test-demo:export",
          "system:dict:query",
          "bpm:model:delete",
          "promotion:coupon-template:delete",
          "pay:app:query",
          "infra:test-demo:query",
          "promotion:coupon:query",
          "product:spu:delete",
          "pay:order:delete",
          "system:notice:create",
          "product:property:delete",
          "system:notify-template:query",
          "infra:job:delete",
          "infra:test-demo:update",
          "market:banner:delete",
          "system:post:update",
          "system:oauth2-client:delete",
          "product:spu:create",
          "promotion:reward-activity:update",
          "system:tenant:create",
          "system:mail-account:update",
          "trade:after-sale:query",
          "report:go-view-project:query",
          "pay:merchant:export",
          "promotion:discount-activity:create",
          "mp:free-publish:submit",
          "system:error-code:update",
          "system:post:export",
          "infra:data-source-config:create",
          "infra:job:trigger",
          "system:sms-channel:update",
          "system:sms-channel:query",
          "mp:account:create",
          "system:login-log:query",
          "mp:material:delete",
          "system:role:update",
          "trade:express-company:delete",
          "mp:tag:query",
          "system:notice:delete",
          "product:category:update",
          "system:login-log:export",
          "system:notify-template:send-notify",
          "promotion:discount-activity:close",
          "product:property:update",
          "system:notify-template:delete",
          "pay:merchant:query",
          "system:permission:assign-user-role",
          "system:post:delete",
          "pay:order:update",
          "mp:free-publish:delete",
          "infra:config:update",
          "mp:tag:delete",
          "infra:job:update",
          "bpm:task-assign-rule:update",
          "market:banner:update",
          "pay:refund:create",
          "pay:app:delete",
          "product:property:query",
          "bpm:model:query",
          "promotion:seckill-activity:delete",
          "system:error-code:export",
          "system:permission:assign-role-menu",
          "infra:config:query",
          "promotion:reward-activity:query",
          "bpm:user-group:update",
          "pay:merchant:update",
          "infra:file-config:delete",
          "infra:codegen:preview",
          "bpm:process-instance:query",
          "system:dict:create",
          "mp:free-publish:query",
          "system:oauth2-token:delete",
          "system:notice:query",
          "promotion:coupon-template:query",
          "infra:file:query",
          "pay:app:update",
          "mp:account:delete",
          "promotion:reward-activity:create",
          "mp:auto-reply:update",
          "infra:config:delete",
          "system:user:update-password",
          "promotion:seckill-activity:query",
          "bpm:form:create",
          "system:oauth2-token:page",
          "mp:statistics:query",
          "system:mail-account:query",
          "system:post:query",
          "system:sms-template:export",
          "pay:merchant:create",
          "infra:build:list",
          "infra:codegen:update",
          "bpm:task:update",
          "infra:data-source-config:export",
          "system:user:import",
          "infra:swagger:list",
          "pay:app:create",
          "system:user:update",
          "promotion:seckill-activity:create",
          "system:menu:delete",
          "system:sms-template:query",
          "promotion:coupon:delete",
          "promotion:reward-activity:delete",
          "mp:menu:query",
          "mp:message:send",
          "system:user:list",
          "product:property:create",
          "infra:codegen:query",
          "infra:test-demo:delete",
          "mp:menu:save",
          "promotion:discount-activity:update",
          "report:go-view-project:create",
          "product:spu:update",
          "system:tenant:delete",
          "mp:menu:delete",
          "mp:account:qr-code",
          "mp:account:clear-quota",
          "mp:user:update",
          "system:role:create",
          "bpm:form:delete",
          "mp:user:query",
          "system:dict:delete",
          "product:brand:update"
      ],
      "menus": [
          {
              "name": "Java",
              "permission": "",
              "type": 1,
              "sort": 0,
              "parentId": 0,
              "path": "/java", 
              "icon": "people",
              "component": "blog/springboot/index",
              "status": 0,
              "visible": true,
              "keepAlive": true,
              "alwaysShow": null,
              "id": 0,
              "createTime": "2022-04-23T01:03:15.000+00:00",
              "children": null
          },
          {
              "name": "Spring Boot",
              "permission": "",
              "type": 1,
              "sort": 1,
              "parentId": 0,
              "path": "/spring-boot",
              "icon": "education",
              "component": "blog/springboot/index",
              "status": 0,
              "visible": true,
              "keepAlive": true,
              "alwaysShow": null,
              "id": 1,
              "createTime": "2023-02-10T22:46:28.000+00:00",
              "children": null
          },
          {
              "name": "BigData",
              "permission": "",
              "type": 1,
              "sort": 2,
              "parentId": 0,
              "path": "/bit-data",
              "icon": "documentation",
              "component": "blog/springboot/index",
              "status": 0,
              "visible": true,
              "keepAlive": true,
              "alwaysShow": null,
              "id": 2,
              "createTime": "2023-02-10T22:47:07.000+00:00",
              "children": null
          },
          {
            "name": "AI",
            "permission": "",
            "type": 1,
            "sort": 3,
            "parentId": 0,
            "path": "/ai",
            "icon": "documentation",
            "component": "blog/springboot/index",
            "status": 0,
            "visible": true,
            "keepAlive": true,
            "alwaysShow": null,
            "id": 3,
            "createTime": "2023-02-10T22:47:07.000+00:00",
            "children": null
        },
          {
              "name": "系统管理",
              "permission": "",
              "type": 1,
              "sort": 10,
              "parentId": 0,
              "path": "/system",
              "icon": "system",
              "component": null,
              "status": 0,
              "visible": true,
              "keepAlive": true,
              "alwaysShow": null,
              "id": 1,
              "createTime": "2021-01-05T17:03:48.000+00:00",
              "children": [
                  {
                      "name": "租户管理",
                      "permission": "",
                      "type": 2,
                      "sort": 0,
                      "parentId": 1,
                      "path": "tenant",
                      "icon": "peoples",
                      "component": null,
                      "status": 0,
                      "visible": true,
                      "keepAlive": true,
                      "alwaysShow": null,
                      "id": 1224,
                      "createTime": "2022-02-20T01:41:13.000+00:00",
                      "children": [
                          {
                              "name": "租户列表",
                              "permission": "",
                              "type": 2,
                              "sort": 0,
                              "parentId": 1224,
                              "path": "list",
                              "icon": "peoples",
                              "component": "system/tenant/index",
                              "status": 0,
                              "visible": true,
                              "keepAlive": true,
                              "alwaysShow": null,
                              "id": 1138,
                              "createTime": "2021-12-14T12:31:43.000+00:00",
                              "children": null
                          },
                          {
                              "name": "租户套餐",
                              "permission": "",
                              "type": 2,
                              "sort": 0,
                              "parentId": 1224,
                              "path": "package",
                              "icon": "eye",
                              "component": "system/tenantPackage/index",
                              "status": 0,
                              "visible": true,
                              "keepAlive": true,
                              "alwaysShow": null,
                              "id": 1225,
                              "createTime": "2022-02-19T17:44:06.000+00:00",
                              "children": null
                          }
                      ]
                  },
                  {
                      "name": "用户管理",
                      "permission": "system:user:list",
                      "type": 2,
                      "sort": 1,
                      "parentId": 1,
                      "path": "user",
                      "icon": "user",
                      "component": "system/user/index",
                      "status": 0,
                      "visible": true,
                      "keepAlive": true,
                      "alwaysShow": null,
                      "id": 100,
                      "createTime": "2021-01-05T17:03:48.000+00:00",
                      "children": null
                  },
                  {
                      "name": "角色管理",
                      "permission": "",
                      "type": 2,
                      "sort": 2,
                      "parentId": 1,
                      "path": "role",
                      "icon": "peoples",
                      "component": "system/role/index",
                      "status": 0,
                      "visible": true,
                      "keepAlive": true,
                      "alwaysShow": null,
                      "id": 101,
                      "createTime": "2021-01-05T17:03:48.000+00:00",
                      "children": null
                  },
                  {
                      "name": "菜单管理",
                      "permission": "",
                      "type": 2,
                      "sort": 3,
                      "parentId": 1,
                      "path": "menu",
                      "icon": "tree-table",
                      "component": "system/menu/index",
                      "status": 0,
                      "visible": true,
                      "keepAlive": true,
                      "alwaysShow": null,
                      "id": 102,
                      "createTime": "2021-01-05T17:03:48.000+00:00",
                      "children": null
                  },
                  {
                      "name": "部门管理",
                      "permission": "",
                      "type": 2,
                      "sort": 4,
                      "parentId": 1,
                      "path": "dept",
                      "icon": "tree",
                      "component": "system/dept/index",
                      "status": 0,
                      "visible": true,
                      "keepAlive": true,
                      "alwaysShow": null,
                      "id": 103,
                      "createTime": "2021-01-05T17:03:48.000+00:00",
                      "children": null
                  },
                  {
                      "name": "岗位管理",
                      "permission": "",
                      "type": 2,
                      "sort": 5,
                      "parentId": 1,
                      "path": "post",
                      "icon": "post",
                      "component": "system/post/index",
                      "status": 0,
                      "visible": true,
                      "keepAlive": true,
                      "alwaysShow": null,
                      "id": 104,
                      "createTime": "2021-01-05T17:03:48.000+00:00",
                      "children": null
                  },
                  {
                      "name": "字典管理",
                      "permission": "",
                      "type": 2,
                      "sort": 6,
                      "parentId": 1,
                      "path": "dict",
                      "icon": "dict",
                      "component": "system/dict/index",
                      "status": 0,
                      "visible": true,
                      "keepAlive": true,
                      "alwaysShow": null,
                      "id": 105,
                      "createTime": "2021-01-05T17:03:48.000+00:00",
                      "children": null
                  },
                  {
                      "name": "通知公告",
                      "permission": "",
                      "type": 2,
                      "sort": 8,
                      "parentId": 1,
                      "path": "notice",
                      "icon": "message",
                      "component": "system/notice/index",
                      "status": 0,
                      "visible": true,
                      "keepAlive": true,
                      "alwaysShow": null,
                      "id": 107,
                      "createTime": "2021-01-05T17:03:48.000+00:00",
                      "children": null
                  },
                  {
                      "name": "审计日志",
                      "permission": "",
                      "type": 1,
                      "sort": 9,
                      "parentId": 1,
                      "path": "log",
                      "icon": "log",
                      "component": "",
                      "status": 0,
                      "visible": true,
                      "keepAlive": true,
                      "alwaysShow": null,
                      "id": 108,
                      "createTime": "2021-01-05T17:03:48.000+00:00",
                      "children": [
                          {
                              "name": "操作日志",
                              "permission": "",
                              "type": 2,
                              "sort": 1,
                              "parentId": 108,
                              "path": "operate-log",
                              "icon": "form",
                              "component": "system/operatelog/index",
                              "status": 0,
                              "visible": true,
                              "keepAlive": true,
                              "alwaysShow": null,
                              "id": 500,
                              "createTime": "2021-01-05T17:03:48.000+00:00",
                              "children": null
                          },
                          {
                              "name": "登录日志",
                              "permission": "",
                              "type": 2,
                              "sort": 2,
                              "parentId": 108,
                              "path": "login-log",
                              "icon": "logininfor",
                              "component": "system/loginlog/index",
                              "status": 0,
                              "visible": true,
                              "keepAlive": true,
                              "alwaysShow": null,
                              "id": 501,
                              "createTime": "2021-01-05T17:03:48.000+00:00",
                              "children": null
                          }
                      ]
                  },
                  {
                      "name": "OAuth 2.0",
                      "permission": "",
                      "type": 1,
                      "sort": 10,
                      "parentId": 1,
                      "path": "oauth2",
                      "icon": "people",
                      "component": null,
                      "status": 0,
                      "visible": true,
                      "keepAlive": true,
                      "alwaysShow": null,
                      "id": 1261,
                      "createTime": "2022-05-09T23:38:17.000+00:00",
                      "children": [
                          {
                              "name": "应用管理",
                              "permission": "",
                              "type": 2,
                              "sort": 0,
                              "parentId": 1261,
                              "path": "oauth2/application",
                              "icon": "tool",
                              "component": "system/oauth2/client/index",
                              "status": 0,
                              "visible": true,
                              "keepAlive": true,
                              "alwaysShow": null,
                              "id": 1263,
                              "createTime": "2022-05-10T16:26:33.000+00:00",
                              "children": null
                          },
                          {
                              "name": "令牌管理",
                              "permission": "",
                              "type": 2,
                              "sort": 2,
                              "parentId": 1261,
                              "path": "token",
                              "icon": "online",
                              "component": "system/oauth2/token/index",
                              "status": 0,
                              "visible": true,
                              "keepAlive": true,
                              "alwaysShow": null,
                              "id": 109,
                              "createTime": "2021-01-05T17:03:48.000+00:00",
                              "children": null
                          }
                      ]
                  },
                  {
                      "name": "短信管理",
                      "permission": "",
                      "type": 1,
                      "sort": 11,
                      "parentId": 1,
                      "path": "sms",
                      "icon": "validCode",
                      "component": null,
                      "status": 0,
                      "visible": true,
                      "keepAlive": true,
                      "alwaysShow": null,
                      "id": 1093,
                      "createTime": "2021-04-05T01:10:16.000+00:00",
                      "children": [
                          {
                              "name": "短信渠道",
                              "permission": "",
                              "type": 2,
                              "sort": 0,
                              "parentId": 1093,
                              "path": "sms-channel",
                              "icon": "phone",
                              "component": "system/sms/channel/index",
                              "status": 0,
                              "visible": true,
                              "keepAlive": true,
                              "alwaysShow": null,
                              "id": 1094,
                              "createTime": "2021-04-01T11:07:15.000+00:00",
                              "children": null
                          },
                          {
                              "name": "短信模板",
                              "permission": "",
                              "type": 2,
                              "sort": 1,
                              "parentId": 1093,
                              "path": "sms-template",
                              "icon": "phone",
                              "component": "system/sms/template/index",
                              "status": 0,
                              "visible": true,
                              "keepAlive": true,
                              "alwaysShow": null,
                              "id": 1100,
                              "createTime": "2021-04-01T17:35:17.000+00:00",
                              "children": null
                          },
                          {
                              "name": "短信日志",
                              "permission": "",
                              "type": 2,
                              "sort": 2,
                              "parentId": 1093,
                              "path": "sms-log",
                              "icon": "phone",
                              "component": "system/sms/log/index",
                              "status": 0,
                              "visible": true,
                              "keepAlive": true,
                              "alwaysShow": null,
                              "id": 1107,
                              "createTime": "2021-04-11T08:37:05.000+00:00",
                              "children": null
                          }
                      ]
                  },
                  {
                      "name": "邮箱管理",
                      "permission": "",
                      "type": 2,
                      "sort": 11,
                      "parentId": 1,
                      "path": "mail",
                      "icon": "email",
                      "component": null,
                      "status": 0,
                      "visible": true,
                      "keepAlive": true,
                      "alwaysShow": null,
                      "id": 2130,
                      "createTime": "2023-01-25T17:27:44.000+00:00",
                      "children": [
                          {
                              "name": "邮箱账号",
                              "permission": "",
                              "type": 2,
                              "sort": 0,
                              "parentId": 2130,
                              "path": "mail-account",
                              "icon": "user",
                              "component": "system/mail/account/index",
                              "status": 0,
                              "visible": true,
                              "keepAlive": true,
                              "alwaysShow": null,
                              "id": 2131,
                              "createTime": "2023-01-25T09:33:48.000+00:00",
                              "children": null
                          },
                          {
                              "name": "邮件模版",
                              "permission": "",
                              "type": 2,
                              "sort": 0,
                              "parentId": 2130,
                              "path": "mail-template",
                              "icon": "education",
                              "component": "system/mail/template/index",
                              "status": 0,
                              "visible": true,
                              "keepAlive": true,
                              "alwaysShow": null,
                              "id": 2136,
                              "createTime": "2023-01-25T12:05:31.000+00:00",
                              "children": null
                          },
                          {
                              "name": "邮件记录",
                              "permission": "",
                              "type": 2,
                              "sort": 0,
                              "parentId": 2130,
                              "path": "mail-log",
                              "icon": "log",
                              "component": "system/mail/log/index",
                              "status": 0,
                              "visible": true,
                              "keepAlive": true,
                              "alwaysShow": null,
                              "id": 2141,
                              "createTime": "2023-01-26T02:16:50.000+00:00",
                              "children": null
                          }
                      ]
                  },
                  {
                      "name": "站内信管理",
                      "permission": "",
                      "type": 1,
                      "sort": 11,
                      "parentId": 1,
                      "path": "notify",
                      "icon": "message",
                      "component": null,
                      "status": 0,
                      "visible": true,
                      "keepAlive": true,
                      "alwaysShow": null,
                      "id": 2144,
                      "createTime": "2023-01-28T10:25:18.000+00:00",
                      "children": [
                          {
                              "name": "模板管理",
                              "permission": "",
                              "type": 2,
                              "sort": 0,
                              "parentId": 2144,
                              "path": "notify-template",
                              "icon": "education",
                              "component": "system/notify/template/index",
                              "status": 0,
                              "visible": true,
                              "keepAlive": true,
                              "alwaysShow": null,
                              "id": 2145,
                              "createTime": "2023-01-28T02:26:42.000+00:00",
                              "children": null
                          },
                          {
                              "name": "消息记录",
                              "permission": "",
                              "type": 2,
                              "sort": 0,
                              "parentId": 2144,
                              "path": "notify-message",
                              "icon": "edit",
                              "component": "system/notify/message/index",
                              "status": 0,
                              "visible": true,
                              "keepAlive": true,
                              "alwaysShow": null,
                              "id": 2151,
                              "createTime": "2023-01-28T04:28:22.000+00:00",
                              "children": null
                          }
                      ]
                  },
                  {
                      "name": "错误码管理",
                      "permission": "",
                      "type": 2,
                      "sort": 12,
                      "parentId": 1,
                      "path": "error-code",
                      "icon": "code",
                      "component": "system/errorCode/index",
                      "status": 0,
                      "visible": true,
                      "keepAlive": true,
                      "alwaysShow": null,
                      "id": 1110,
                      "createTime": "2021-04-13T21:46:42.000+00:00",
                      "children": null
                  },
                  {
                      "name": "敏感词管理",
                      "permission": "",
                      "type": 2,
                      "sort": 13,
                      "parentId": 1,
                      "path": "sensitive-word",
                      "icon": "education",
                      "component": "system/sensitiveWord/index",
                      "status": 0,
                      "visible": true,
                      "keepAlive": true,
                      "alwaysShow": null,
                      "id": 1247,
                      "createTime": "2022-04-07T16:55:03.000+00:00",
                      "children": null
                  },
                  {
                      "name": "地区管理",
                      "permission": "",
                      "type": 2,
                      "sort": 14,
                      "parentId": 1,
                      "path": "area",
                      "icon": "row",
                      "component": "system/area/index",
                      "status": 0,
                      "visible": true,
                      "keepAlive": true,
                      "alwaysShow": null,
                      "id": 2083,
                      "createTime": "2022-12-23T17:35:05.000+00:00",
                      "children": null
                  }
              ]
          },
          {
              "name": "基础设施",
              "permission": "",
              "type": 1,
              "sort": 20,
              "parentId": 0,
              "path": "/infra",
              "icon": "monitor",
              "component": null,
              "status": 0,
              "visible": true,
              "keepAlive": true,
              "alwaysShow": null,
              "id": 2,
              "createTime": "2021-01-05T17:03:48.000+00:00",
              "children": [
                  {
                      "name": "代码生成",
                      "permission": "infra:codegen:query",
                      "type": 2,
                      "sort": 1,
                      "parentId": 2,
                      "path": "codegen",
                      "icon": "code",
                      "component": "infra/codegen/index",
                      "status": 0,
                      "visible": true,
                      "keepAlive": true,
                      "alwaysShow": null,
                      "id": 115,
                      "createTime": "2021-01-05T17:03:48.000+00:00",
                      "children": null
                  },
                  {
                      "name": "代码生成示例",
                      "permission": "infra:test-demo:query",
                      "type": 2,
                      "sort": 1,
                      "parentId": 2,
                      "path": "test-demo",
                      "icon": "validCode",
                      "component": "infra/testDemo/index",
                      "status": 0,
                      "visible": true,
                      "keepAlive": true,
                      "alwaysShow": null,
                      "id": 1070,
                      "createTime": "2021-02-06T12:42:49.000+00:00",
                      "children": null
                  },
                  {
                      "name": "数据源配置",
                      "permission": "",
                      "type": 2,
                      "sort": 1,
                      "parentId": 2,
                      "path": "data-source-config",
                      "icon": "rate",
                      "component": "infra/dataSourceConfig/index",
                      "status": 0,
                      "visible": true,
                      "keepAlive": true,
                      "alwaysShow": null,
                      "id": 1255,
                      "createTime": "2022-04-27T14:37:32.000+00:00",
                      "children": null
                  },
                  {
                      "name": "表单构建",
                      "permission": "infra:build:list",
                      "type": 2,
                      "sort": 2,
                      "parentId": 2,
                      "path": "build",
                      "icon": "build",
                      "component": "infra/build/index",
                      "status": 0,
                      "visible": true,
                      "keepAlive": true,
                      "alwaysShow": null,
                      "id": 114,
                      "createTime": "2021-01-05T17:03:48.000+00:00",
                      "children": null
                  },
                  {
                      "name": "系统接口",
                      "permission": "infra:swagger:list",
                      "type": 2,
                      "sort": 3,
                      "parentId": 2,
                      "path": "swagger",
                      "icon": "swagger",
                      "component": "infra/swagger/index",
                      "status": 0,
                      "visible": true,
                      "keepAlive": true,
                      "alwaysShow": null,
                      "id": 116,
                      "createTime": "2021-01-05T17:03:48.000+00:00",
                      "children": null
                  },
                  {
                      "name": "数据库文档",
                      "permission": "",
                      "type": 2,
                      "sort": 4,
                      "parentId": 2,
                      "path": "db-doc",
                      "icon": "table",
                      "component": "infra/dbDoc/index",
                      "status": 0,
                      "visible": true,
                      "keepAlive": true,
                      "alwaysShow": null,
                      "id": 1076,
                      "createTime": "2021-02-08T01:41:47.000+00:00",
                      "children": null
                  },
                  {
                      "name": "文件管理",
                      "permission": "",
                      "type": 2,
                      "sort": 5,
                      "parentId": 2,
                      "path": "file",
                      "icon": "download",
                      "component": null,
                      "status": 0,
                      "visible": true,
                      "keepAlive": true,
                      "alwaysShow": null,
                      "id": 1243,
                      "createTime": "2022-03-16T23:47:40.000+00:00",
                      "children": [
                          {
                              "name": "文件配置",
                              "permission": "",
                              "type": 2,
                              "sort": 0,
                              "parentId": 1243,
                              "path": "file-config",
                              "icon": "config",
                              "component": "infra/fileConfig/index",
                              "status": 0,
                              "visible": true,
                              "keepAlive": true,
                              "alwaysShow": null,
                              "id": 1237,
                              "createTime": "2022-03-15T14:35:28.000+00:00",
                              "children": null
                          },
                          {
                              "name": "文件列表",
                              "permission": "",
                              "type": 2,
                              "sort": 5,
                              "parentId": 1243,
                              "path": "file",
                              "icon": "upload",
                              "component": "infra/file/index",
                              "status": 0,
                              "visible": true,
                              "keepAlive": true,
                              "alwaysShow": null,
                              "id": 1090,
                              "createTime": "2021-03-12T20:16:20.000+00:00",
                              "children": null
                          }
                      ]
                  },
                  {
                      "name": "配置管理",
                      "permission": "",
                      "type": 2,
                      "sort": 6,
                      "parentId": 2,
                      "path": "config",
                      "icon": "edit",
                      "component": "infra/config/index",
                      "status": 0,
                      "visible": true,
                      "keepAlive": true,
                      "alwaysShow": null,
                      "id": 106,
                      "createTime": "2021-01-05T17:03:48.000+00:00",
                      "children": null
                  },
                  {
                      "name": "API 日志",
                      "permission": "",
                      "type": 2,
                      "sort": 8,
                      "parentId": 2,
                      "path": "log",
                      "icon": "log",
                      "component": null,
                      "status": 0,
                      "visible": true,
                      "keepAlive": true,
                      "alwaysShow": null,
                      "id": 1083,
                      "createTime": "2021-02-26T02:18:24.000+00:00",
                      "children": [
                          {
                              "name": "访问日志",
                              "permission": "",
                              "type": 2,
                              "sort": 1,
                              "parentId": 1083,
                              "path": "api-access-log",
                              "icon": "log",
                              "component": "infra/apiAccessLog/index",
                              "status": 0,
                              "visible": true,
                              "keepAlive": true,
                              "alwaysShow": null,
                              "id": 1078,
                              "createTime": "2021-02-26T01:32:59.000+00:00",
                              "children": null
                          },
                          {
                              "name": "错误日志",
                              "permission": "infra:api-error-log:query",
                              "type": 2,
                              "sort": 2,
                              "parentId": 1083,
                              "path": "api-error-log",
                              "icon": "log",
                              "component": "infra/apiErrorLog/index",
                              "status": 0,
                              "visible": true,
                              "keepAlive": true,
                              "alwaysShow": null,
                              "id": 1084,
                              "createTime": "2021-02-26T07:53:20.000+00:00",
                              "children": null
                          }
                      ]
                  },
                  {
                      "name": "MySQL 监控",
                      "permission": "",
                      "type": 2,
                      "sort": 9,
                      "parentId": 2,
                      "path": "druid",
                      "icon": "druid",
                      "component": "infra/druid/index",
                      "status": 0,
                      "visible": true,
                      "keepAlive": true,
                      "alwaysShow": null,
                      "id": 111,
                      "createTime": "2021-01-05T17:03:48.000+00:00",
                      "children": null
                  },
                  {
                      "name": "Redis 监控",
                      "permission": "",
                      "type": 2,
                      "sort": 10,
                      "parentId": 2,
                      "path": "redis",
                      "icon": "redis",
                      "component": "infra/redis/index",
                      "status": 0,
                      "visible": true,
                      "keepAlive": true,
                      "alwaysShow": null,
                      "id": 113,
                      "createTime": "2021-01-05T17:03:48.000+00:00",
                      "children": null
                  },
                  {
                      "name": "Java 监控",
                      "permission": "",
                      "type": 2,
                      "sort": 11,
                      "parentId": 2,
                      "path": "admin-server",
                      "icon": "server",
                      "component": "infra/server/index",
                      "status": 0,
                      "visible": true,
                      "keepAlive": true,
                      "alwaysShow": null,
                      "id": 112,
                      "createTime": "2021-01-05T17:03:48.000+00:00",
                      "children": null
                  },
                  {
                      "name": "定时任务",
                      "permission": "",
                      "type": 2,
                      "sort": 12,
                      "parentId": 2,
                      "path": "job",
                      "icon": "job",
                      "component": "infra/job/index",
                      "status": 0,
                      "visible": true,
                      "keepAlive": true,
                      "alwaysShow": null,
                      "id": 110,
                      "createTime": "2021-01-05T17:03:48.000+00:00",
                      "children": null
                  },
                  {
                      "name": "监控平台",
                      "permission": "",
                      "type": 2,
                      "sort": 13,
                      "parentId": 2,
                      "path": "skywalking",
                      "icon": "eye-open",
                      "component": "infra/skywalking/index",
                      "status": 0,
                      "visible": true,
                      "keepAlive": true,
                      "alwaysShow": null,
                      "id": 1077,
                      "createTime": "2021-02-08T20:41:31.000+00:00",
                      "children": null
                  }
              ]
          },
          {
              "name": "支付管理",
              "permission": "",
              "type": 1,
              "sort": 30,
              "parentId": 0,
              "path": "/pay",
              "icon": "money",
              "component": null,
              "status": 0,
              "visible": true,
              "keepAlive": true,
              "alwaysShow": null,
              "id": 1117,
              "createTime": "2021-12-25T16:43:41.000+00:00",
              "children": [
                  {
                      "name": "商户信息",
                      "permission": "",
                      "type": 2,
                      "sort": 0,
                      "parentId": 1117,
                      "path": "merchant",
                      "icon": "merchant",
                      "component": "pay/merchant/index",
                      "status": 0,
                      "visible": true,
                      "keepAlive": true,
                      "alwaysShow": null,
                      "id": 1179,
                      "createTime": "2021-12-25T09:01:44.000+00:00",
                      "children": null
                  },
                  {
                      "name": "应用信息",
                      "permission": "",
                      "type": 2,
                      "sort": 1,
                      "parentId": 1117,
                      "path": "app",
                      "icon": "table",
                      "component": "pay/app/index",
                      "status": 0,
                      "visible": true,
                      "keepAlive": true,
                      "alwaysShow": null,
                      "id": 1126,
                      "createTime": "2021-11-10T01:13:30.000+00:00",
                      "children": null
                  },
                  {
                      "name": "支付订单",
                      "permission": "",
                      "type": 2,
                      "sort": 2,
                      "parentId": 1117,
                      "path": "order",
                      "icon": "pay",
                      "component": "pay/order/index",
                      "status": 0,
                      "visible": true,
                      "keepAlive": true,
                      "alwaysShow": null,
                      "id": 1173,
                      "createTime": "2021-12-25T08:49:43.000+00:00",
                      "children": null
                  },
                  {
                      "name": "退款订单",
                      "permission": "",
                      "type": 2,
                      "sort": 3,
                      "parentId": 1117,
                      "path": "refund",
                      "icon": "order",
                      "component": "pay/refund/index",
                      "status": 0,
                      "visible": true,
                      "keepAlive": true,
                      "alwaysShow": null,
                      "id": 1161,
                      "createTime": "2021-12-25T08:29:07.000+00:00",
                      "children": null
                  },
                  {
                      "name": "接入示例",
                      "permission": "",
                      "type": 2,
                      "sort": 99,
                      "parentId": 1117,
                      "path": "demo-order",
                      "icon": "drag",
                      "component": "pay/demo/index",
                      "status": 0,
                      "visible": true,
                      "keepAlive": true,
                      "alwaysShow": null,
                      "id": 2161,
                      "createTime": "2023-02-11T14:21:42.000+00:00",
                      "children": null
                  }
              ]
          },
          {
              "name": "报表管理",
              "permission": "",
              "type": 1,
              "sort": 40,
              "parentId": 0,
              "path": "/report",
              "icon": "chart",
              "component": null,
              "status": 0,
              "visible": true,
              "keepAlive": true,
              "alwaysShow": null,
              "id": 1281,
              "createTime": "2022-07-10T20:22:15.000+00:00",
              "children": [
                  {
                      "name": "报表设计器",
                      "permission": "",
                      "type": 2,
                      "sort": 1,
                      "parentId": 1281,
                      "path": "jimu-report",
                      "icon": "example",
                      "component": "report/jmreport/index",
                      "status": 0,
                      "visible": true,
                      "keepAlive": true,
                      "alwaysShow": null,
                      "id": 1282,
                      "createTime": "2022-07-10T20:26:36.000+00:00",
                      "children": null
                  },
                  {
                      "name": "大屏设计器",
                      "permission": "",
                      "type": 2,
                      "sort": 2,
                      "parentId": 1281,
                      "path": "go-view",
                      "icon": "dashboard",
                      "component": "report/goview/index",
                      "status": 0,
                      "visible": true,
                      "keepAlive": true,
                      "alwaysShow": null,
                      "id": 2153,
                      "createTime": "2023-02-07T00:03:19.000+00:00",
                      "children": null
                  }
              ]
          },
          {
              "name": "工作流程",
              "permission": "",
              "type": 1,
              "sort": 50,
              "parentId": 0,
              "path": "/bpm",
              "icon": "tool",
              "component": null,
              "status": 0,
              "visible": true,
              "keepAlive": true,
              "alwaysShow": null,
              "id": 1185,
              "createTime": "2021-12-30T20:26:36.000+00:00",
              "children": [
                  {
                      "name": "流程管理",
                      "permission": "",
                      "type": 1,
                      "sort": 10,
                      "parentId": 1185,
                      "path": "manager",
                      "icon": "nested",
                      "component": null,
                      "status": 0,
                      "visible": true,
                      "keepAlive": true,
                      "alwaysShow": null,
                      "id": 1186,
                      "createTime": "2021-12-30T20:28:30.000+00:00",
                      "children": [
                          {
                              "name": "流程表单",
                              "permission": "",
                              "type": 2,
                              "sort": 0,
                              "parentId": 1186,
                              "path": "form",
                              "icon": "form",
                              "component": "bpm/form/index",
                              "status": 0,
                              "visible": true,
                              "keepAlive": true,
                              "alwaysShow": null,
                              "id": 1187,
                              "createTime": "2021-12-30T12:38:22.000+00:00",
                              "children": null
                          },
                          {
                              "name": "用户分组",
                              "permission": "",
                              "type": 2,
                              "sort": 2,
                              "parentId": 1186,
                              "path": "user-group",
                              "icon": "people",
                              "component": "bpm/group/index",
                              "status": 0,
                              "visible": true,
                              "keepAlive": true,
                              "alwaysShow": null,
                              "id": 1209,
                              "createTime": "2022-01-14T02:14:20.000+00:00",
                              "children": null
                          },
                          {
                              "name": "流程模型",
                              "permission": "",
                              "type": 2,
                              "sort": 5,
                              "parentId": 1186,
                              "path": "model",
                              "icon": "guide",
                              "component": "bpm/model/index",
                              "status": 0,
                              "visible": true,
                              "keepAlive": true,
                              "alwaysShow": null,
                              "id": 1193,
                              "createTime": "2021-12-31T23:24:58.000+00:00",
                              "children": null
                          }
                      ]
                  },
                  {
                      "name": "任务管理",
                      "permission": "",
                      "type": 1,
                      "sort": 20,
                      "parentId": 1185,
                      "path": "task",
                      "icon": "cascader",
                      "component": null,
                      "status": 0,
                      "visible": true,
                      "keepAlive": true,
                      "alwaysShow": null,
                      "id": 1200,
                      "createTime": "2022-01-07T23:51:48.000+00:00",
                      "children": [
                          {
                              "name": "我的流程",
                              "permission": "",
                              "type": 2,
                              "sort": 0,
                              "parentId": 1200,
                              "path": "my",
                              "icon": "people",
                              "component": "bpm/processInstance/index",
                              "status": 0,
                              "visible": true,
                              "keepAlive": true,
                              "alwaysShow": null,
                              "id": 1201,
                              "createTime": "2022-01-07T15:53:44.000+00:00",
                              "children": null
                          },
                          {
                              "name": "待办任务",
                              "permission": "",
                              "type": 2,
                              "sort": 10,
                              "parentId": 1200,
                              "path": "todo",
                              "icon": "eye-open",
                              "component": "bpm/task/todo/index",
                              "status": 0,
                              "visible": true,
                              "keepAlive": true,
                              "alwaysShow": null,
                              "id": 1207,
                              "createTime": "2022-01-08T10:33:37.000+00:00",
                              "children": null
                          },
                          {
                              "name": "已办任务",
                              "permission": "",
                              "type": 2,
                              "sort": 20,
                              "parentId": 1200,
                              "path": "done",
                              "icon": "eye",
                              "component": "bpm/task/done/index",
                              "status": 0,
                              "visible": true,
                              "keepAlive": true,
                              "alwaysShow": null,
                              "id": 1208,
                              "createTime": "2022-01-08T10:34:13.000+00:00",
                              "children": null
                          }
                      ]
                  },
                  {
                      "name": "OA 示例",
                      "permission": "",
                      "type": 1,
                      "sort": 40,
                      "parentId": 1185,
                      "path": "oa",
                      "icon": "people",
                      "component": null,
                      "status": 0,
                      "visible": true,
                      "keepAlive": true,
                      "alwaysShow": null,
                      "id": 5,
                      "createTime": "2021-09-20T16:26:19.000+00:00",
                      "children": [
                          {
                              "name": "请假查询",
                              "permission": "",
                              "type": 2,
                              "sort": 0,
                              "parentId": 5,
                              "path": "leave",
                              "icon": "user",
                              "component": "bpm/oa/leave/index",
                              "status": 0,
                              "visible": true,
                              "keepAlive": true,
                              "alwaysShow": null,
                              "id": 1118,
                              "createTime": "2021-09-20T08:51:03.000+00:00",
                              "children": null
                          }
                      ]
                  }
              ]
          },
          {
              "name": "商品中心",
              "permission": "",
              "type": 1,
              "sort": 60,
              "parentId": 0,
              "path": "/product",
              "icon": "merchant",
              "component": null,
              "status": 0,
              "visible": true,
              "keepAlive": true,
              "alwaysShow": null,
              "id": 2000,
              "createTime": "2022-07-29T15:53:53.000+00:00",
              "children": [
                  {
                      "name": "商品列表",
                      "permission": "",
                      "type": 2,
                      "sort": 1,
                      "parentId": 2000,
                      "path": "spu",
                      "icon": "list",
                      "component": "mall/product/spu/index",
                      "status": 0,
                      "visible": true,
                      "keepAlive": true,
                      "alwaysShow": null,
                      "id": 2014,
                      "createTime": "2022-07-30T14:22:58.000+00:00",
                      "children": null
                  },
                  {
                      "name": "商品分类",
                      "permission": "",
                      "type": 2,
                      "sort": 2,
                      "parentId": 2000,
                      "path": "category",
                      "icon": "dict",
                      "component": "mall/product/category/index",
                      "status": 0,
                      "visible": true,
                      "keepAlive": true,
                      "alwaysShow": null,
                      "id": 2002,
                      "createTime": "2022-07-29T15:53:53.000+00:00",
                      "children": null
                  },
                  {
                      "name": "商品品牌",
                      "permission": "",
                      "type": 2,
                      "sort": 3,
                      "parentId": 2000,
                      "path": "brand",
                      "icon": "dashboard",
                      "component": "mall/product/brand/index",
                      "status": 0,
                      "visible": true,
                      "keepAlive": true,
                      "alwaysShow": null,
                      "id": 2008,
                      "createTime": "2022-07-30T13:52:44.000+00:00",
                      "children": null
                  },
                  {
                      "name": "商品属性",
                      "permission": "",
                      "type": 2,
                      "sort": 3,
                      "parentId": 2000,
                      "path": "property",
                      "icon": "eye",
                      "component": "mall/product/property/index",
                      "status": 0,
                      "visible": true,
                      "keepAlive": true,
                      "alwaysShow": null,
                      "id": 2019,
                      "createTime": "2022-08-01T14:55:35.000+00:00",
                      "children": null
                  },
                  {
                      "name": "Banner管理",
                      "permission": "",
                      "type": 2,
                      "sort": 100,
                      "parentId": 2000,
                      "path": "banner",
                      "icon": "",
                      "component": "mall/market/banner/index",
                      "status": 0,
                      "visible": true,
                      "keepAlive": true,
                      "alwaysShow": null,
                      "id": 2025,
                      "createTime": "2022-08-01T14:56:14.000+00:00",
                      "children": null
                  }
              ]
          },
          {
              "name": "订单中心",
              "permission": "",
              "type": 1,
              "sort": 65,
              "parentId": 0,
              "path": "/trade",
              "icon": "order",
              "component": null,
              "status": 0,
              "visible": true,
              "keepAlive": true,
              "alwaysShow": null,
              "id": 2072,
              "createTime": "2022-11-19T18:57:19.000+00:00",
              "children": [
                  {
                      "name": "订单列表",
                      "permission": "",
                      "type": 2,
                      "sort": 0,
                      "parentId": 2072,
                      "path": "trade/order",
                      "icon": "list",
                      "component": "mall/trade/order/index",
                      "status": 0,
                      "visible": true,
                      "keepAlive": true,
                      "alwaysShow": null,
                      "id": 2076,
                      "createTime": "2022-12-10T21:05:44.000+00:00",
                      "children": null
                  },
                  {
                      "name": "物流公司管理管理",
                      "permission": "",
                      "type": 2,
                      "sort": 0,
                      "parentId": 2072,
                      "path": "express-company",
                      "icon": "",
                      "component": "mall/trade/expressCompany/index",
                      "status": 0,
                      "visible": true,
                      "keepAlive": true,
                      "alwaysShow": null,
                      "id": 2077,
                      "createTime": "2022-12-20T23:27:55.000+00:00",
                      "children": null
                  },
                  {
                      "name": "售后退款",
                      "permission": "",
                      "type": 2,
                      "sort": 1,
                      "parentId": 2072,
                      "path": "trade/after-sale",
                      "icon": "education",
                      "component": "mall/trade/afterSale/index",
                      "status": 0,
                      "visible": true,
                      "keepAlive": true,
                      "alwaysShow": null,
                      "id": 2073,
                      "createTime": "2022-11-19T20:15:32.000+00:00",
                      "children": null
                  }
              ]
          },
          {
              "name": "营销中心",
              "permission": "",
              "type": 1,
              "sort": 70,
              "parentId": 0,
              "path": "/promotion",
              "icon": "rate",
              "component": null,
              "status": 0,
              "visible": true,
              "keepAlive": true,
              "alwaysShow": null,
              "id": 2030,
              "createTime": "2022-10-31T21:25:09.000+00:00",
              "children": [
                  {
                      "name": "秒杀活动管理",
                      "permission": "",
                      "type": 2,
                      "sort": 0,
                      "parentId": 2030,
                      "path": "seckill-activity",
                      "icon": "time-range",
                      "component": "mall/promotion/seckill/seckillActivity/index",
                      "status": 0,
                      "visible": true,
                      "keepAlive": true,
                      "alwaysShow": null,
                      "id": 2059,
                      "createTime": "2022-11-06T22:24:49.000+00:00",
                      "children": null
                  },
                  {
                      "name": "秒杀时段管理",
                      "permission": "",
                      "type": 2,
                      "sort": 0,
                      "parentId": 2030,
                      "path": "seckill-time",
                      "icon": "",
                      "component": "mall/promotion/seckill/seckillTime/index",
                      "status": 0,
                      "visible": false,
                      "keepAlive": true,
                      "alwaysShow": null,
                      "id": 2066,
                      "createTime": "2022-11-15T19:46:50.000+00:00",
                      "children": null
                  },
                  {
                      "name": "优惠劵",
                      "permission": "",
                      "type": 2,
                      "sort": 2,
                      "parentId": 2030,
                      "path": "coupon-template",
                      "icon": "textarea",
                      "component": "mall/promotion/couponTemplate/index",
                      "status": 0,
                      "visible": true,
                      "keepAlive": true,
                      "alwaysShow": null,
                      "id": 2032,
                      "createTime": "2022-10-31T22:27:14.000+00:00",
                      "children": null
                  },
                  {
                      "name": "会员优惠劵",
                      "permission": "",
                      "type": 2,
                      "sort": 2,
                      "parentId": 2030,
                      "path": "coupon",
                      "icon": "",
                      "component": "mall/promotion/coupon/index",
                      "status": 0,
                      "visible": false,
                      "keepAlive": true,
                      "alwaysShow": null,
                      "id": 2038,
                      "createTime": "2022-11-03T23:21:31.000+00:00",
                      "children": null
                  },
                  {
                      "name": "限时折扣活动",
                      "permission": "",
                      "type": 2,
                      "sort": 7,
                      "parentId": 2030,
                      "path": "discount-activity",
                      "icon": "time",
                      "component": "mall/promotion/discountActivity/index",
                      "status": 0,
                      "visible": true,
                      "keepAlive": true,
                      "alwaysShow": null,
                      "id": 2047,
                      "createTime": "2022-11-05T17:12:15.000+00:00",
                      "children": null
                  },
                  {
                      "name": "满减送活动",
                      "permission": "",
                      "type": 2,
                      "sort": 10,
                      "parentId": 2030,
                      "path": "reward-activity",
                      "icon": "radio",
                      "component": "mall/promotion/rewardActivity/index",
                      "status": 0,
                      "visible": true,
                      "keepAlive": true,
                      "alwaysShow": null,
                      "id": 2041,
                      "createTime": "2022-11-04T23:47:49.000+00:00",
                      "children": null
                  }
              ]
          },
          {
              "name": "公众号管理",
              "permission": "",
              "type": 1,
              "sort": 100,
              "parentId": 0,
              "path": "/mp",
              "icon": "wechat",
              "component": null,
              "status": 0,
              "visible": true,
              "keepAlive": true,
              "alwaysShow": null,
              "id": 2084,
              "createTime": "2023-01-01T20:11:04.000+00:00",
              "children": [
                  {
                      "name": "账号管理",
                      "permission": "",
                      "type": 2,
                      "sort": 1,
                      "parentId": 2084,
                      "path": "account",
                      "icon": "phone",
                      "component": "mp/account/index",
                      "status": 0,
                      "visible": true,
                      "keepAlive": true,
                      "alwaysShow": null,
                      "id": 2085,
                      "createTime": "2023-01-01T20:13:31.000+00:00",
                      "children": null
                  },
                  {
                      "name": "数据统计",
                      "permission": "mp:statistics:query",
                      "type": 2,
                      "sort": 2,
                      "parentId": 2084,
                      "path": "statistics",
                      "icon": "chart",
                      "component": "mp/statistics/index",
                      "status": 0,
                      "visible": true,
                      "keepAlive": true,
                      "alwaysShow": null,
                      "id": 2092,
                      "createTime": "2023-01-07T20:17:36.000+00:00",
                      "children": null
                  },
                  {
                      "name": "标签管理",
                      "permission": "",
                      "type": 2,
                      "sort": 3,
                      "parentId": 2084,
                      "path": "tag",
                      "icon": "rate",
                      "component": "mp/tag/index",
                      "status": 0,
                      "visible": true,
                      "keepAlive": true,
                      "alwaysShow": null,
                      "id": 2093,
                      "createTime": "2023-01-08T11:37:32.000+00:00",
                      "children": null
                  },
                  {
                      "name": "粉丝管理",
                      "permission": "",
                      "type": 2,
                      "sort": 4,
                      "parentId": 2084,
                      "path": "user",
                      "icon": "people",
                      "component": "mp/user/index",
                      "status": 0,
                      "visible": true,
                      "keepAlive": true,
                      "alwaysShow": null,
                      "id": 2099,
                      "createTime": "2023-01-08T16:51:20.000+00:00",
                      "children": null
                  },
                  {
                      "name": "消息管理",
                      "permission": "",
                      "type": 2,
                      "sort": 5,
                      "parentId": 2084,
                      "path": "message",
                      "icon": "email",
                      "component": "mp/message/index",
                      "status": 0,
                      "visible": true,
                      "keepAlive": true,
                      "alwaysShow": null,
                      "id": 2103,
                      "createTime": "2023-01-08T18:44:19.000+00:00",
                      "children": null
                  },
                  {
                      "name": "菜单管理",
                      "permission": "",
                      "type": 2,
                      "sort": 6,
                      "parentId": 2084,
                      "path": "menu",
                      "icon": "button",
                      "component": "mp/menu/index",
                      "status": 0,
                      "visible": true,
                      "keepAlive": true,
                      "alwaysShow": null,
                      "id": 2119,
                      "createTime": "2023-01-14T17:43:54.000+00:00",
                      "children": null
                  },
                  {
                      "name": "自动回复",
                      "permission": "",
                      "type": 2,
                      "sort": 7,
                      "parentId": 2084,
                      "path": "auto-reply",
                      "icon": "eye",
                      "component": "mp/autoReply/index",
                      "status": 0,
                      "visible": true,
                      "keepAlive": true,
                      "alwaysShow": null,
                      "id": 2120,
                      "createTime": "2023-01-15T22:13:09.000+00:00",
                      "children": null
                  },
                  {
                      "name": "素材管理",
                      "permission": "",
                      "type": 2,
                      "sort": 8,
                      "parentId": 2084,
                      "path": "material",
                      "icon": "skill",
                      "component": "mp/material/index",
                      "status": 0,
                      "visible": true,
                      "keepAlive": true,
                      "alwaysShow": null,
                      "id": 2113,
                      "createTime": "2023-01-14T14:12:07.000+00:00",
                      "children": null
                  },
                  {
                      "name": "图文草稿箱",
                      "permission": "",
                      "type": 2,
                      "sort": 9,
                      "parentId": 2084,
                      "path": "draft",
                      "icon": "edit",
                      "component": "mp/draft/index",
                      "status": 0,
                      "visible": true,
                      "keepAlive": true,
                      "alwaysShow": null,
                      "id": 2108,
                      "createTime": "2023-01-13T07:40:21.000+00:00",
                      "children": null
                  },
                  {
                      "name": "图文发表记录",
                      "permission": "",
                      "type": 2,
                      "sort": 10,
                      "parentId": 2084,
                      "path": "free-publish",
                      "icon": "education",
                      "component": "mp/freePublish/index",
                      "status": 0,
                      "visible": true,
                      "keepAlive": true,
                      "alwaysShow": null,
                      "id": 2104,
                      "createTime": "2023-01-13T00:30:50.000+00:00",
                      "children": null
                  }
              ]
          }
      ]
  },
  "msg": ""
}